vtkpython_cbl/__init__.py
vtkpython_cbl/addLocalBasisToBiV.py
vtkpython_cbl/addLocalBasisToLV.py
vtkpython_cbl/clipSurfacesForCutLVMesh.py
vtkpython_cbl/clipSurfacesForFullBiVMesh.py
vtkpython_cbl/clipSurfacesForFullLVMesh.py
vtkpython_cbl/exportDynaDeformationGradients.py
vtkpython_cbl/extendEpicardialSurface.py
vtkpython_cbl/getABPointsFromBoundsAndCenter.py
vtkpython_cbl/getABPointsFromOrientedBoundingBox.py
vtkpython_cbl/getABPointsFromTTTSectors.py
vtkpython_cbl/getCartesianCoordinates.py
vtkpython_cbl/getCylindricalCoordinatesAndBasis.py
vtkpython_cbl/getFiberDirections.py
vtkpython_cbl/getFiberSheetNormalDirections.py
vtkpython_cbl/getFractionalAnisotropy.py
vtkpython_cbl/getHelixAngles.py
vtkpython_cbl/getHelixTransverseSheetAngles.py
vtkpython_cbl/getHelixTransverseSheetAngles2.py
vtkpython_cbl/getMeanStddevAngles.py
vtkpython_cbl/getPCA.py
vtkpython_cbl/getPrincipalDirections.py
vtkpython_cbl/getPseudoProlateSpheroidalCoordinatesAndBasis.py
vtkpython_cbl/getRegions.py
vtkpython_cbl/getSectors.py
vtkpython_cbl/getSyntheticHelixAngles.py
vtkpython_cbl/getSyntheticHelixAngles2.py
vtkpython_cbl/getSyntheticHelixTransverseSheetAngles.py
vtkpython_cbl/getSystolicStrainsFromEndDiastolicAndEndSystolicDeformationGradients.py
vtkpython_cbl/readAbaqusFibersFromINP.py
vtkpython_cbl/splitDomainBetweenEndoAndEpi.py
vtkpython_cbl/writeFiberOrientationFileForAbaqus.py
vtkpython_cbl/writeFiberOrientationFileForGNUPlot.py
vtkpython_cbl-2025.4.17.data/scripts/addLocalBasisToBiV.py
vtkpython_cbl-2025.4.17.data/scripts/addLocalBasisToLV.py
vtkpython_cbl-2025.4.17.data/scripts/clipSurfacesForCutLVMesh.py
vtkpython_cbl-2025.4.17.data/scripts/clipSurfacesForFullBiVMesh.py
vtkpython_cbl-2025.4.17.data/scripts/clipSurfacesForFullLVMesh.py
vtkpython_cbl-2025.4.17.data/scripts/extendEpicardialSurface.py
vtkpython_cbl-2025.4.17.data/scripts/splitDomainBetweenEndoAndEpi.py
vtkpython_cbl-2025.4.17.dist-info/licenses/LICENSE
vtkpython_cbl-2025.4.17.dist-info/METADATA
vtkpython_cbl-2025.4.17.dist-info/WHEEL
vtkpython_cbl-2025.4.17.dist-info/top_level.txt
vtkpython_cbl-2025.4.17.dist-info/RECORD
