Metadata-Version: 2.4
Name: vtkpython_cbl
Version: 2025.4.17
Summary: A library of vtkpython tools for cardiac biomechanics.
Home-page: https://gitlab.inria.fr/mgenet/vtkpython_cbl
Author: Martin Genet
Author-email: martin.genet@polytechnique.edu
License: GPLv3
Classifier: Programming Language :: Python :: 3
Classifier: License :: OSI Approved :: GNU General Public License v3 (GPLv3)
Classifier: Operating System :: OS Independent
License-File: LICENSE
Requires-Dist: numpy
Requires-Dist: vtk
Requires-Dist: myPythonLibrary
Requires-Dist: myVTKPythonLibrary
Dynamic: author
Dynamic: author-email
Dynamic: classifier
Dynamic: description
Dynamic: description-content-type
Dynamic: home-page
Dynamic: license
Dynamic: license-file
Dynamic: requires-dist
Dynamic: summary
